airium/__init__.py
airium/__main__.py
airium/forward.py
airium/py.typed
airium/reverse.py
airium-0.2.7.dist-info/licenses/LICENSE
airium-0.2.7.dist-info/METADATA
airium-0.2.7.dist-info/WHEEL
airium-0.2.7.dist-info/entry_points.txt
airium-0.2.7.dist-info/top_level.txt
airium-0.2.7.dist-info/RECORD
