Metadata-Version: 2.4
Name: airium
Version: 0.2.7
Summary: Easy and quick html builder with natural syntax correspondence (python->html). No templates needed. Serves pure pythonic library with no dependencies.
Home-page: https://gitlab.com/kamichal/airium
Author: Michał Kaczmarczyk
Author-email: michal.s.kaczmarczyk@gmail.com
Maintainer: Michał Kaczmarczyk
Maintainer-email: michal.s.kaczmarczyk@gmail.com
License: MIT
Keywords: natural html generator compiler template-less
Classifier: Development Status :: 4 - Beta
Classifier: Intended Audience :: Developers
Classifier: Intended Audience :: Information Technology
Classifier: Intended Audience :: Science/Research
Classifier: Intended Audience :: System Administrators
Classifier: Intended Audience :: Telecommunications Industry
Classifier: Operating System :: OS Independent
Classifier: Programming Language :: Python :: 3
Classifier: Programming Language :: Python :: 3.8
Classifier: Programming Language :: Python :: 3.9
Classifier: Programming Language :: Python :: 3.10
Classifier: Programming Language :: Python :: 3.11
Classifier: Programming Language :: Python :: 3.12
Classifier: Programming Language :: Python :: 3.13
Classifier: Programming Language :: Python :: Implementation :: PyPy
Classifier: Programming Language :: Python
Classifier: Topic :: Database :: Front-Ends
Classifier: Topic :: Documentation
Classifier: Topic :: Internet :: WWW/HTTP :: Browsers
Classifier: Topic :: Internet :: WWW/HTTP :: Dynamic Content
Classifier: Topic :: Internet :: WWW/HTTP
Classifier: Topic :: Scientific/Engineering :: Visualization
Classifier: Topic :: Software Development :: Code Generators
Classifier: Topic :: Text Processing :: Markup :: HTML
Classifier: Topic :: Utilities
License-File: LICENSE
Provides-Extra: dev
Requires-Dist: check-manifest; extra == "dev"
Requires-Dist: flake8~=7.1; extra == "dev"
Requires-Dist: mypy~=1.10; extra == "dev"
Requires-Dist: pytest-cov~=3.0; extra == "dev"
Requires-Dist: pytest-mock~=3.6; extra == "dev"
Requires-Dist: pytest~=6.2; extra == "dev"
Requires-Dist: types-beautifulsoup4~=4.12; extra == "dev"
Requires-Dist: types-requests~=2.32; extra == "dev"
Provides-Extra: parse
Requires-Dist: requests<3,>=2.12.0; extra == "parse"
Requires-Dist: beautifulsoup4<5.0,>=4.10.0; extra == "parse"
Dynamic: author
Dynamic: author-email
Dynamic: classifier
Dynamic: description
Dynamic: description-content-type
Dynamic: home-page
Dynamic: keywords
Dynamic: license
Dynamic: license-file
Dynamic: maintainer
Dynamic: maintainer-email
Dynamic: provides-extra
Dynamic: summary
